refchaser/__init__.py
refchaser/__main__.py
refchaser/bibparser.py
refchaser/bioreader.py
refchaser/massdownlit.py
refchaser/querydatabase.py
refchaser/refchaser.py
refchaser-0.0.3.dist-info/METADATA
refchaser-0.0.3.dist-info/WHEEL
refchaser-0.0.3.dist-info/top_level.txt
refchaser-0.0.3.dist-info/RECORD
