Metadata-Version: 2.1
Name: refchaser
Version: 0.0.3
Summary: Written in python, for checking reference lists in systematic reviews and literature reviews, helps with reference list searching both backward & forward by extracting references and creating search queries, ranks articles by relevance to improve screening efficiency, downloads full-text pdf of research articles in batch.
Home-page: https://github.com/DQ-Zhang/refchaser.git
Author-email: zhangdingqi1998@gmail.com
License: UNKNOWN
Platform: UNKNOWN
Classifier: Development Status :: 3 - Alpha
Classifier: Intended Audience :: Science/Research
Classifier: Intended Audience :: Healthcare Industry
Classifier: Intended Audience :: Education
Classifier: Topic :: Scientific/Engineering
Classifier: Programming Language :: Python :: 3
Classifier: License :: OSI Approved :: MIT License
Classifier: Operating System :: Microsoft :: Windows
Requires-Python: >=3
